datalayers/main.py
datalayers-0.1.1.dist-info/LICENSE
datalayers-0.1.1.dist-info/WHEEL
datalayers-0.1.1.dist-info/METADATA
datalayers-0.1.1.dist-info/RECORD
